recordsql/__init__.py
recordsql/base.py
recordsql/dependencies/__init__.py
recordsql/integrations/tablesqlite/__init__.py
recordsql/integrations/tablesqlite/count.py
recordsql/integrations/tablesqlite/delete.py
recordsql/integrations/tablesqlite/exists.py
recordsql/integrations/tablesqlite/insert.py
recordsql/integrations/tablesqlite/main.py
recordsql/integrations/tablesqlite/select.py
recordsql/integrations/tablesqlite/update.py
recordsql/query/__init__.py
recordsql/query/count.py
recordsql/query/delete.py
recordsql/query/exists.py
recordsql/query/insert.py
recordsql/query/select.py
recordsql/query/update.py
recordsql/query/utils.py
recordsql/raw_querybuilders/__init__.py
recordsql/raw_querybuilders/count.py
recordsql/raw_querybuilders/delete.py
recordsql/raw_querybuilders/exists.py
recordsql/raw_querybuilders/formatters.py
recordsql/raw_querybuilders/insert.py
recordsql/raw_querybuilders/select.py
recordsql/raw_querybuilders/update.py
recordsql/raw_querybuilders/utils.py
recordsql/types.py
recordsql/utils.py
recordsql/validators.py
recordsql-0.2.1.dist-info/METADATA
recordsql-0.2.1.dist-info/WHEEL
recordsql-0.2.1.dist-info/licenses/LICENSE
recordsql-0.2.1.dist-info/RECORD
