Metadata-Version: 2.4
Name: recordsql
Version: 0.2.1
Summary: A Python-based SQL query builder with a fluent and composable interface, built on expressql.
License-Expression: MIT
License-File: LICENSE
Keywords: SQL,query-builder,Python,DSL,expressql,chained comparisons,placeholder,SQL conditions,CTE,JOIN
Author: Grayjou
Author-email: cgrayjou@gmail.com
Requires-Python: >=3.9,<4.0
Classifier: Development Status :: 3 - Alpha
Classifier: Intended Audience :: Developers
Classifier: Programming Language :: Python :: 3
Classifier: Programming Language :: Python :: 3.9
Classifier: Programming Language :: Python :: 3.10
Classifier: Programming Language :: Python :: 3.11
Classifier: Programming Language :: Python :: 3.12
Classifier: Programming Language :: Python :: 3.13
Classifier: Programming Language :: Python :: 3.14
Classifier: Topic :: Database
Classifier: Topic :: Software Development :: Libraries :: Python Modules
Requires-Dist: expressql (==1.0.0)
Project-URL: Documentation, https://github.com/Grayjou/recordsql#readme
Project-URL: Homepage, https://github.com/Grayjou/recordsql
Project-URL: Repository, https://github.com/Grayjou/recordsql
